{
  "version": 2,
  "tree": {
    "name": "root",
    "children": [
      {
        "name": "index.esm.js",
        "children": [
          {
            "name": "src",
            "children": [
              {
                "uid": "f890-6",
                "name": "VisuallyHidden.tsx"
              },
              {
                "uid": "f890-8",
                "name": "index.ts"
              }
            ]
          }
        ]
      }
    ],
    "isRoot": true
  },
  "nodeParts": {
    "f890-6": {
      "renderedLength": 405,
      "gzipLength": 283,
      "brotliLength": 223,
      "mainUid": "f890-5"
    },
    "f890-8": {
      "renderedLength": 0,
      "gzipLength": 0,
      "brotliLength": 0,
      "mainUid": "f890-7"
    }
  },
  "nodeMetas": {
    "f890-5": {
      "id": "/src/VisuallyHidden.tsx",
      "moduleParts": {
        "index.esm.js": "f890-6"
      },
      "imported": [
        {
          "uid": "f890-9"
        }
      ],
      "importedBy": [
        {
          "uid": "f890-7"
        }
      ]
    },
    "f890-7": {
      "id": "/src/index.ts",
      "moduleParts": {
        "index.esm.js": "f890-8"
      },
      "imported": [
        {
          "uid": "f890-5"
        }
      ],
      "importedBy": [],
      "isEntry": true
    },
    "f890-9": {
      "id": "styled-components",
      "moduleParts": {},
      "imported": [],
      "importedBy": [
        {
          "uid": "f890-5"
        }
      ],
      "isExternal": true
    }
  },
  "env": {
    "rollup": "2.63.0"
  },
  "options": {
    "gzip": true,
    "brotli": true,
    "sourcemap": false
  }
}